[
  {
    "name": "car",
    "class": 2,
    "confidence": 0.90557,
    "box": {
      "x1": 1234.38062,
      "y1": 411.39355,
      "x2": 1403.24817,
      "y2": 545.60376
    },
    "track_id": 1
  },
  {
    "name": "car",
    "class": 2,
    "confidence": 0.87358,
    "box": {
      "x1": 0.88293,
      "y1": 61.24902,
      "x2": 581.15497,
      "y2": 945.97015
    },
    "track_id": 2
  },
  {
    "name": "car",
    "class": 2,
    "confidence": 0.85719,
    "box": {
      "x1": 1011.31903,
      "y1": 407.28714,
      "x2": 1124.44165,
      "y2": 501.51035
    },
    "track_id": 3
  },
  {
    "name": "car",
    "class": 2,
    "confidence": 0.85365,
    "box": {
      "x1": 905.23999,
      "y1": 408.95743,
      "x2": 999.48724,
      "y2": 473.3956
    },
    "track_id": 4
  },
  {
    "name": "traffic light",
    "class": 9,
    "confidence": 0.5378,
    "box": {
      "x1": 1094.84631,
      "y1": 252.06708,
      "x2": 1106.07654,
      "y2": 285.89062
    },
    "track_id": 5
  },
  {
    "name": "traffic light",
    "class": 9,
    "confidence": 0.47863,
    "box": {
      "x1": 1032.49365,
      "y1": 106.50792,
      "x2": 1051.32605,
      "y2": 169.86691
    },
    "track_id": 6
  },
  {
    "name": "truck",
    "class": 7,
    "confidence": 0.46552,
    "box": {
      "x1": 1168.88708,
      "y1": 384.11102,
      "x2": 1265.07458,
      "y2": 481.81161
    },
    "track_id": 7
  },
  {
    "name": "traffic light",
    "class": 9,
    "confidence": 0.42251,
    "box": {
      "x1": 1191.37769,
      "y1": 252.92822,
      "x2": 1205.76282,
      "y2": 287.30597
    },
    "track_id": 8
  },
  {
    "name": "traffic light",
    "class": 9,
    "confidence": 0.38778,
    "box": {
      "x1": 692.74915,
      "y1": 273.88571,
      "x2": 717.61676,
      "y2": 333.10587
    },
    "track_id": 9
  },
  {
    "name": "car",
    "class": 2,
    "confidence": 0.38776,
    "box": {
      "x1": 1123.39575,
      "y1": 417.53897,
      "x2": 1157.81287,
      "y2": 445.12082
    },
    "track_id": 10
  },
  {
    "name": "car",
    "class": 2,
    "confidence": 0.33433,
    "box": {
      "x1": 1168.81348,
      "y1": 385.23413,
      "x2": 1265.10962,
      "y2": 481.67447
    },
    "track_id": 11
  }
]